mielelogic/__init__.py
mielelogic/helperclasses.py
mielelogic/miele.py
mielelogic-0.0.19.dist-info/LICENSE
mielelogic-0.0.19.dist-info/METADATA
mielelogic-0.0.19.dist-info/WHEEL
mielelogic-0.0.19.dist-info/top_level.txt
mielelogic-0.0.19.dist-info/RECORD
