Metadata-Version: 2.1
Name: mielelogic
Version: 0.0.19
Summary: API interface for MieleLogic.com
Home-page: https://github.com/PTST/MieleLogic
Author: PTST
Author-email: patrick@steffensen.io
License: UNKNOWN
Platform: UNKNOWN
Classifier: Programming Language :: Python :: 3
Classifier: License :: OSI Approved :: MIT License
Classifier: Operating System :: OS Independent
Requires-Python: >=3.6
Requires-Dist: requests (>=2.21.0)
